.gitignore
README.rst
composite-example.py
readthedocs.yml
setup.py
test.py
docs/Makefile
docs/api_reference.rst
docs/conf.py
docs/index.rst
docs/install.rst
docs/intro.rst
docs/make.bat
docs/quickstart.rst
dynamongo/__init__.py
dynamongo/conditions.py
dynamongo/connection.py
dynamongo/exceptions.py
dynamongo/fields.py
dynamongo/model.py
dynamongo/updates.py
dynamongo/utils.py
dynamongo.egg-info/PKG-INFO
dynamongo.egg-info/SOURCES.txt
dynamongo.egg-info/dependency_links.txt
dynamongo.egg-info/not-zip-safe
dynamongo.egg-info/requires.txt
dynamongo.egg-info/top_level.txt