Metadata-Version: 1.1
Name: dynamongo
Version: 0.1
Summary: A lightweight library for interacting with AWS dynamoDB in a pythonic way,inspired by pymongo
Home-page: https://github.com/musyoka-morris/dynamongo
Author: Musyoka Morris
Author-email: musyokamorris@gmail.com
License: MIT
Keywords: aws,dynamo,dynamodb,ormserialization,deserialization,validation
Platform: UNKNOWN
Classifier: Development Status :: 5 - Production/Stable
Classifier: Intended Audience :: Developers
Classifier: License :: OSI Approved :: MIT License
Classifier: Operating System :: OS Independent
Classifier: Programming Language :: Python :: 3
Classifier: Programming Language :: Python :: 3.5
Classifier: Programming Language :: Python :: 3.6
Classifier: Programming Language :: Python :: Implementation :: PyPy
Classifier: Topic :: Software Development :: Libraries
